meysam_utils/__init__.py
meysam_utils/logger.py
meysam_utils/random_.py
meysam_utils/settings.py
meysam_utils-0.1.0.dist-info/METADATA
meysam_utils-0.1.0.dist-info/WHEEL
meysam_utils-0.1.0.dist-info/top_level.txt
meysam_utils-0.1.0.dist-info/RECORD
