Metadata-Version: 2.1
Name: meysam-utils
Version: 0.1.0
Summary: A set of repetitive utilities that I'm using everywhere with the same code
Requires-Python: >=3.7
Provides-Extra: all
Requires-Dist: pydantic (<2) ; extra == 'all'
Provides-Extra: settings
Requires-Dist: pydantic (<2) ; extra == 'settings'
